pyp3/__init__.py
pyp3/__main__.py
pyp3-1.0.0.dist-info/LICENSE
pyp3-1.0.0.dist-info/METADATA
pyp3-1.0.0.dist-info/WHEEL
pyp3-1.0.0.dist-info/entry_points.txt
pyp3-1.0.0.dist-info/top_level.txt
pyp3-1.0.0.dist-info/RECORD
