Metadata-Version: 2.1
Name: pyp3
Version: 1.0.0
Summary: Pyp is a linux command line text manipulation tool similar to awk or sed, but which uses standard python string and list methods as well as custom functions evolved to generate fast results in an intense production environment.
Home-page: https://github.com/donno2048/pyp3
Author: Elisha Hollander
Author-email: just4now666666@gmail.com
License: UNKNOWN
Project-URL: Documentation, https://github.com/donno2048/pyp3#readme
Project-URL: Bug Reports, https://github.com/donno2048/pyp3/issues
Project-URL: Source Code, https://github.com/donno2048/pyp3
Platform: UNKNOWN
Classifier: Programming Language :: Python :: 3
Requires-Python: >=3.0
